djangocms_filer_display_pages_where_files_are_used_before_removing_them/__init__.py
djangocms_filer_display_pages_where_files_are_used_before_removing_them/apps.py
djangocms_filer_display_pages_where_files_are_used_before_removing_them/locale/fr/LC_MESSAGES/django.mo
djangocms_filer_display_pages_where_files_are_used_before_removing_them/locale/fr/LC_MESSAGES/django.po
djangocms_filer_display_pages_where_files_are_used_before_removing_them/templates/admin/delete_confirmation.html
djangocms_filer_display_pages_where_files_are_used_before_removing_them/templates/admin/filer/delete_confirmation.html
djangocms_filer_display_pages_where_files_are_used_before_removing_them/templates/admin/filer/delete_selected_files_confirmation.html
djangocms_filer_display_pages_where_files_are_used_before_removing_them/templatetags/__init__.py
djangocms_filer_display_pages_where_files_are_used_before_removing_them/templatetags/get_page_list_from_object.py
djangocms_filer_display_pages_where_files_are_used_before_removing_them-0.3.0.dist-info/AUTHORS.md
djangocms_filer_display_pages_where_files_are_used_before_removing_them-0.3.0.dist-info/LICENSE
djangocms_filer_display_pages_where_files_are_used_before_removing_them-0.3.0.dist-info/METADATA
djangocms_filer_display_pages_where_files_are_used_before_removing_them-0.3.0.dist-info/WHEEL
djangocms_filer_display_pages_where_files_are_used_before_removing_them-0.3.0.dist-info/top_level.txt
djangocms_filer_display_pages_where_files_are_used_before_removing_them-0.3.0.dist-info/RECORD
