Metadata-Version: 2.1
Name: djangocms-filer-display-pages-where-files-are-used-before-removing-them
Version: 0.3.0
Summary: Show locations of images & other files before deleting them.
Home-page: https://gitlab.com/kapt/open-source/djangocms-filer-display-pages-where-files-are-used-before-removing-them
Author: Corentin Bettiol
Author-email: dev@kapt.mobi
Classifier: Environment :: Web Environment
Classifier: Framework :: Django
Classifier: Framework :: Django CMS
Classifier: Intended Audience :: Developers
Classifier: License :: OSI Approved :: GNU General Public License v3 (GPLv3)
Classifier: Programming Language :: Python
Classifier: Programming Language :: Python :: 3
Classifier: Topic :: Internet :: WWW/HTTP
Classifier: Topic :: Internet :: WWW/HTTP :: Dynamic Content
License-File: LICENSE
License-File: AUTHORS.md
Requires-Dist: django-filer
